tgcrypto.cpython-39-i386-linux-gnu.so
tests/__init__.py
tests/ige/__init__.py
tests/ige/test_ige.py
tests/ctr/__init__.py
tests/ctr/test_ctr.py
tests/cbc/__init__.py
tests/cbc/test_cbc.py
hasnainkkCrypto-1.0.0.dist-info/METADATA
hasnainkkCrypto-1.0.0.dist-info/RECORD
hasnainkkCrypto-1.0.0.dist-info/top_level.txt
hasnainkkCrypto-1.0.0.dist-info/NOTICE
hasnainkkCrypto-1.0.0.dist-info/COPYING.lesser
hasnainkkCrypto-1.0.0.dist-info/WHEEL
hasnainkkCrypto-1.0.0.dist-info/COPYING
